flux0_cli/__init__.py
flux0_cli/main.py
flux0_cli/py.typed
flux0_cli/cmds/agents.py
flux0_cli/cmds/sessions.py
flux0_cli/utils/decorators.py
flux0_cli/utils/output.py
flux0_cli-0.1.0b1.dist-info/METADATA
flux0_cli-0.1.0b1.dist-info/WHEEL
flux0_cli-0.1.0b1.dist-info/RECORD
